{
    "architectural": {
        "buildings": [
            "modern skyscraper",
            "gothic cathedral",
            "art deco tower",
            "minimalist villa",
            "classical museum",
            "contemporary gallery",
            "brutalist complex",
            "renaissance palace",
            "glass office building",
            "sustainable eco-building",
            "historic mansion",
            "modernist house",
            "cultural center",
            "innovative pavilion",
            "urban mixed-use complex"
        ],
        "locations": [
            "bustling city center",
            "historic district",
            "waterfront promenade",
            "urban park",
            "financial district",
            "cultural quarter",
            "university campus",
            "residential neighborhood",
            "industrial redevelopment",
            "suburban development"
        ],
        "times": [
            "golden hour",
            "blue hour",
            "sunrise",
            "sunset",
            "midday",
            "twilight",
            "dusk",
            "dawn",
            "night",
            "morning"
        ],
        "weather": [
            "clear sky",
            "dramatic clouds",
            "soft overcast",
            "misty atmosphere",
            "light rain",
            "stormy conditions",
            "snow covered",
            "foggy morning",
            "sunny day",
            "moody atmosphere"
        ],
        "perspectives": [
            "aerial view",
            "street level",
            "low angle",
            "high angle",
            "bird's eye view",
            "worm's eye view",
            "three-quarter view",
            "facade view",
            "interior perspective",
            "architectural cross-section"
        ],
        "lighting": [
            "natural daylight",
            "dramatic spotlighting",
            "ambient illumination",
            "architectural lighting",
            "interior lighting",
            "exterior floodlights",
            "accent lighting",
            "diffused lighting",
            "directional lighting",
            "mood lighting"
        ],
        "atmosphere": [
            "professional",
            "dramatic",
            "serene",
            "dynamic",
            "sophisticated",
            "minimalist",
            "luxurious",
            "industrial",
            "artistic",
            "contemporary"
        ],
        "structures": [
            "building",
            "skyscraper",
            "bridge",
            "museum",
            "cathedral",
            "pavilion",
            "tower",
            "monument",
            "palace",
            "temple",
            "arena",
            "amphitheater",
            "aquarium",
            "library",
            "theater",
            "observatory",
            "cultural center",
            "shopping mall",
            "stadium",
            "community center"
        ],
        "styles": [
            "modern",
            "classical",
            "gothic",
            "baroque",
            "art deco",
            "minimalist",
            "brutalist",
            "renaissance",
            "neoclassical",
            "contemporary"
        ],
        "elements": [
            "columns",
            "arches",
            "domes",
            "facades",
            "windows",
            "staircases",
            "balconies",
            "cornices",
            "pillars",
            "spires"
        ],
        "settings": [
            "cityscape",
            "urban plaza",
            "historic district",
            "cultural center",
            "business district",
            "waterfront",
            "campus",
            "garden",
            "courtyard",
            "skyline"
        ],
        "features": [
            "landscaping",
            "water features",
            "public spaces",
            "green spaces",
            "pathways",
            "terraces",
            "fountains",
            "plazas",
            "gardens",
            "courtyards"
        ],
        "periods": [
            "modern",
            "classical",
            "medieval",
            "renaissance",
            "baroque",
            "victorian",
            "art nouveau",
            "art deco",
            "contemporary",
            "postmodern"
        ],
        "techniques": [
            "perspective drawing",
            "3D modeling",
            "architectural rendering",
            "technical drawing",
            "blueprint style",
            "elevation drawing",
            "isometric view",
            "sectional view",
            "axonometric projection",
            "parametric design"
        ],
        "effects": [
            "reflection",
            "shadow",
            "transparency",
            "texture",
            "pattern",
            "symmetry",
            "proportion",
            "scale",
            "depth",
            "perspective"
        ],
        "principles": [
            "harmony",
            "balance",
            "rhythm",
            "proportion",
            "scale",
            "depth",
            "perspective"
        ]
    }
}